oneurai/__init__.py
oneurai/api.py
oneurai-0.2.9.dist-info/METADATA
oneurai-0.2.9.dist-info/WHEEL
oneurai-0.2.9.dist-info/top_level.txt
oneurai-0.2.9.dist-info/RECORD
