Metadata-Version: 2.1
Name: oneurai
Version: 0.2.9
Summary: A powerful AI client library for Oneurai MLOps platform
Home-page: https://oneurai.com
Author: MTMA
Author-email: mtma.1@hotmail.com
Classifier: Programming Language :: Python :: 3
Classifier: License :: OSI Approved :: MIT License
Classifier: Operating System :: OS Independent
Requires-Python: >=3.7
Requires-Dist: requests
Requires-Dist: torch
Requires-Dist: tqdm
Requires-Dist: colorama
